README
setup.py
groundwork_utilities/__init__.py
groundwork_utilities/resources.py
groundwork_utilities/version.py
groundwork_utilities.egg-info/PKG-INFO
groundwork_utilities.egg-info/SOURCES.txt
groundwork_utilities.egg-info/dependency_links.txt
groundwork_utilities.egg-info/entry_points.txt
groundwork_utilities.egg-info/requires.txt
groundwork_utilities.egg-info/top_level.txt
groundwork_utilities/patterns/__init__.py
groundwork_utilities/patterns/gw_db_validators_pattern/__init__.py
groundwork_utilities/patterns/gw_db_validators_pattern/gw_db_validators.py
groundwork_utilities/patterns/gw_validators_pattern/__init__.py
groundwork_utilities/patterns/gw_validators_pattern/gw_validators_pattern.py
groundwork_utilities/plugins/__init__.py
groundwork_utilities/plugins/GwDbValidator/__init__.py
groundwork_utilities/plugins/GwDbValidator/gw_db_validator.py
groundwork_utilities/plugins/GwResourceMonitor/__init__.py
groundwork_utilities/plugins/GwResourceMonitor/gw_resource_monitor.py
groundwork_utilities/plugins/GwResourceMonitorWeb/__init__.py
groundwork_utilities/recipes/__init__.py